{
  "screens": {
    "start": {
      "text": "Добро пожаловать!",
      "inlineKeyboard": [
        [
          {
            "text": "Подключиться",
            "data": "start_to_join"
          }
        ],
        [
          {
            "text": "Создать комнату",
            "data": "start_to_gameSelect"
          }
        ],
        [
          {
            "text": "Настройки",
            "data": "start_to_settings"
          }
        ]
      ]
    },
    "join": {
      "text": "ПОДКЛЮЧЕНИЕ НЕ РАБОТАЕТ",
      "inlineKeyboard": [
        [
          {
            "text": "Назад",
            "data": "join_to_start"
          }
        ]
      ]
    },
    "gameSelect": {
      "text": "Выберите игру",
      "inlineKeyboard": [
        [
          {
            "text": "Liar`s Bar",
            "data": "gameSelect_to_liarsBar"
          },
          {
            "text": "Взрывные котята",
            "data": "gameSelect_to_cats"
          }
        ],
        [
          {
            "text": "Назад",
            "data": "gameSelect_to_start"
          }
        ]
      ]
    },
    "settings": {
      "text": "Настройки",
      "inlineKeyboard": [
        [
          {
            "text": "Изменить имя",
            "data": "settings_to_changeName"
          },
          {
            "text": "Сбросить имя",
            "data": "settings_to_resetName"
          }
        ],
        [
          {
            "text": "Назад",
            "data": "settings_to_start"
          }
        ]
      ]
    },
    "changeName": {
      "text": "Изменить имя НЕ РАБОТАЕТ",
      "inlineKeyboard": [
        [
          {
            "text": "Назад",
            "data": "changeName_to_settings"
          }
        ]
      ]
    },
    "resetName": {
      "text": "Сбросить имя НЕ РАБОТАЕТ",
      "inlineKeyboard": [
        [
          {
            "text": "Назад",
            "data": "resetName_to_settings"
          }
        ]
      ]
    },
    "liarsBar": {
      "text": "Liar`s Bar НЕ РАБОТАЕТ",
      "inlineKeyboard": [
        [
          {
            "text": "Назад",
            "data": "liarsBar_to_gameSelect"
          }
        ]
      ]
    },
    "cats": {
      "text": "Взрывные котята НЕ РАБОТАЕТ",
      "inlineKeyboard": [
        [
          {
            "text": "Назад",
            "data": "cats_to_gameSelect"
          }
        ]
      ]
    }
  }
}